{
    "Meta Data": {
        "1. Information": "Daily Prices (open, high, low, close) and Volumes",
        "2. Symbol": "NFLX",
        "3. Last Refreshed": "2026-03-12",
        "4. Output Size": "Compact",
        "5. Time Zone": "US/Eastern"
    },
    "Time Series (Daily)": {
        "2026-03-12": {
            "1. open": "1010.0000",
            "2. high": "1026.7938",
            "3. low": "1008.2323",
            "4. close": "1022.8651",
            "5. volume": "3447048"
        },
        "2026-03-11": {
            "1. open": "1022.8651",
            "2. high": "1025.6024",
            "3. low": "1010.3492",
            "4. close": "1015.6341",
            "5. volume": "4028723"
        },
        "2026-03-10": {
            "1. open": "1015.6341",
            "2. high": "1020.3964",
            "3. low": "1000.5146",
            "4. close": "1001.8324",
            "5. volume": "6788154"
        },
        "2026-03-09": {
            "1. open": "1001.8324",
            "2. high": "1014.2390",
            "3. low": "999.8911",
            "4. close": "1012.1515",
            "5. volume": "4014336"
        },
        "2026-03-06": {
            "1. open": "1012.1515",
            "2. high": "1033.7861",
            "3. low": "1005.7018",
            "4. close": "1027.1698",
            "5. volume": "5210254"
        },
        "2026-03-05": {
            "1. open": "1027.1698",
            "2. high": "1049.4631",
            "3. low": "1023.9233",
            "4. close": "1042.4839",
            "5. volume": "5415569"
        },
        "2026-03-04": {
            "1. open": "1042.4839",
            "2. high": "1048.4118",
            "3. low": "1038.3337",
            "4. close": "1047.0230",
            "5. volume": "8138138"
        },
        "2026-03-03": {
            "1. open": "1047.0230",
            "2. high": "1048.4327",
            "3. low": "1033.8431",
            "4. close": "1040.1816",
            "5. volume": "7478880"
        },
        "2026-03-02": {
            "1. open": "1040.1816",
            "2. high": "1045.1356",
            "3. low": "1027.5757",
            "4. close": "1031.7226",
            "5. volume": "7678910"
        },
        "2026-02-27": {
            "1. open": "1031.7226",
            "2. high": "1032.8853",
            "3. low": "1021.6258",
            "4. close": "1022.3295",
            "5. volume": "6530428"
        },
        "2026-02-26": {
            "1. open": "1022.3295",
            "2. high": "1025.2069",
            "3. low": "1005.9191",
            "4. close": "1015.6115",
            "5. volume": "5299507"
        },
        "2026-02-25": {
            "1. open": "1015.6115",
            "2. high": "1046.2937",
            "3. low": "1010.7736",
            "4. close": "1041.0432",
            "5. volume": "7164707"
        },
        "2026-02-24": {
            "1. open": "1041.0432",
            "2. high": "1061.1482",
            "3. low": "1039.1101",
            "4. close": "1058.4463",
            "5. volume": "5732355"
        },
        "2026-02-23": {
            "1. open": "1058.4463",
            "2. high": "1080.3106",
            "3. low": "1053.3235",
            "4. close": "1078.1820",
            "5. volume": "8026338"
        },
        "2026-02-20": {
            "1. open": "1078.1820",
            "2. high": "1082.1542",
            "3. low": "1032.1700",
            "4. close": "1042.1469",
            "5. volume": "5761907"
        },
        "2026-02-19": {
            "1. open": "1042.1469",
            "2. high": "1057.0994",
            "3. low": "1029.5101",
            "4. close": "1053.6665",
            "5. volume": "6496471"
        },
        "2026-02-18": {
            "1. open": "1053.6665",
            "2. high": "1062.6500",
            "3. low": "1052.4948",
            "4. close": "1053.1816",
            "5. volume": "7847101"
        },
        "2026-02-17": {
            "1. open": "1053.1816",
            "2. high": "1070.0511",
            "3. low": "1042.0198",
            "4. close": "1059.4654",
            "5. volume": "7763661"
        },
        "2026-02-16": {
            "1. open": "1059.4654",
            "2. high": "1069.5615",
            "3. low": "1057.1445",
            "4. close": "1067.8196",
            "5. volume": "7701228"
        },
        "2026-02-13": {
            "1. open": "1067.8196",
            "2. high": "1086.5054",
            "3. low": "1067.7029",
            "4. close": "1081.3004",
            "5. volume": "7400224"
        },
        "2026-02-12": {
            "1. open": "1081.3004",
            "2. high": "1119.3085",
            "3. low": "1080.6287",
            "4. close": "1111.2544",
            "5. volume": "4544969"
        },
        "2026-02-11": {
            "1. open": "1111.2544",
            "2. high": "1114.5494",
            "3. low": "1095.8642",
            "4. close": "1097.4665",
            "5. volume": "4296467"
        },
        "2026-02-10": {
            "1. open": "1097.4665",
            "2. high": "1133.5280",
            "3. low": "1093.7863",
            "4. close": "1129.5234",
            "5. volume": "5605887"
        },
        "2026-02-09": {
            "1. open": "1129.5234",
            "2. high": "1134.8751",
            "3. low": "1115.7568",
            "4. close": "1118.3762",
            "5. volume": "7759767"
        },
        "2026-02-06": {
            "1. open": "1118.3762",
            "2. high": "1118.9091",
            "3. low": "1105.9300",
            "4. close": "1114.5193",
            "5. volume": "3517804"
        },
        "2026-02-05": {
            "1. open": "1114.5193",
            "2. high": "1118.0758",
            "3. low": "1077.4905",
            "4. close": "1078.2998",
            "5. volume": "7550529"
        },
        "2026-02-04": {
            "1. open": "1078.2998",
            "2. high": "1086.1592",
            "3. low": "1060.9559",
            "4. close": "1062.2290",
            "5. volume": "6614592"
        },
        "2026-02-03": {
            "1. open": "1062.2290",
            "2. high": "1065.1597",
            "3. low": "1054.4305",
            "4. close": "1063.3766",
            "5. volume": "4725457"
        },
        "2026-02-02": {
            "1. open": "1063.3766",
            "2. high": "1064.4068",
            "3. low": "1048.3057",
            "4. close": "1050.2565",
            "5. volume": "6172328"
        },
        "2026-01-30": {
            "1. open": "1050.2565",
            "2. high": "1051.4941",
            "3. low": "1032.1204",
            "4. close": "1034.0284",
            "5. volume": "3770608"
        },
        "2026-01-29": {
            "1. open": "1034.0284",
            "2. high": "1036.1835",
            "3. low": "1028.4480",
            "4. close": "1031.7543",
            "5. volume": "5407847"
        },
        "2026-01-28": {
            "1. open": "1031.7543",
            "2. high": "1034.3614",
            "3. low": "1017.4123",
            "4. close": "1022.9314",
            "5. volume": "5305284"
        },
        "2026-01-27": {
            "1. open": "1022.9314",
            "2. high": "1024.1446",
            "3. low": "1010.3900",
            "4. close": "1011.3155",
            "5. volume": "7082412"
        },
        "2026-01-26": {
            "1. open": "1011.3155",
            "2. high": "1015.5321",
            "3. low": "998.8929",
            "4. close": "1000.6133",
            "5. volume": "3757243"
        },
        "2026-01-23": {
            "1. open": "1000.6133",
            "2. high": "1011.1853",
            "3. low": "965.9621",
            "4. close": "974.0519",
            "5. volume": "7480905"
        },
        "2026-01-22": {
            "1. open": "974.0519",
            "2. high": "1000.1434",
            "3. low": "971.0019",
            "4. close": "992.0443",
            "5. volume": "4522054"
        },
        "2026-01-21": {
            "1. open": "992.0443",
            "2. high": "999.6824",
            "3. low": "983.9604",
            "4. close": "992.0834",
            "5. volume": "3540706"
        },
        "2026-01-20": {
            "1. open": "992.0834",
            "2. high": "992.7697",
            "3. low": "968.3558",
            "4. close": "968.9705",
            "5. volume": "5314367"
        },
        "2026-01-19": {
            "1. open": "968.9705",
            "2. high": "973.0859",
            "3. low": "962.3716",
            "4. close": "971.1615",
            "5. volume": "7750850"
        },
        "2026-01-16": {
            "1. open": "971.1615",
            "2. high": "975.8760",
            "3. low": "937.4266",
            "4. close": "943.7678",
            "5. volume": "6092401"
        },
        "2026-01-15": {
            "1. open": "943.7678",
            "2. high": "951.4806",
            "3. low": "934.6714",
            "4. close": "936.2269",
            "5. volume": "3480894"
        },
        "2026-01-14": {
            "1. open": "936.2269",
            "2. high": "953.0335",
            "3. low": "923.5741",
            "4. close": "952.1190",
            "5. volume": "5391239"
        },
        "2026-01-13": {
            "1. open": "952.1190",
            "2. high": "963.4493",
            "3. low": "929.5295",
            "4. close": "934.8774",
            "5. volume": "7563542"
        },
        "2026-01-12": {
            "1. open": "934.8774",
            "2. high": "941.3574",
            "3. low": "916.5380",
            "4. close": "925.5535",
            "5. volume": "6606118"
        },
        "2026-01-09": {
            "1. open": "925.5535",
            "2. high": "932.0153",
            "3. low": "922.5482",
            "4. close": "928.1830",
            "5. volume": "4418567"
        },
        "2026-01-08": {
            "1. open": "928.1830",
            "2. high": "930.5659",
            "3. low": "912.9274",
            "4. close": "916.5219",
            "5. volume": "5577324"
        },
        "2026-01-07": {
            "1. open": "916.5219",
            "2. high": "921.5175",
            "3. low": "903.3938",
            "4. close": "903.4257",
            "5. volume": "7268492"
        },
        "2026-01-06": {
            "1. open": "903.4257",
            "2. high": "943.4448",
            "3. low": "902.4037",
            "4. close": "934.3824",
            "5. volume": "3484872"
        },
        "2026-01-05": {
            "1. open": "934.3824",
            "2. high": "941.4202",
            "3. low": "930.6019",
            "4. close": "936.5169",
            "5. volume": "4547185"
        },
        "2026-01-02": {
            "1. open": "936.5169",
            "2. high": "939.3919",
            "3. low": "932.5031",
            "4. close": "934.9957",
            "5. volume": "3484463"
        },
        "2026-01-01": {
            "1. open": "934.9957",
            "2. high": "941.5191",
            "3. low": "911.3145",
            "4. close": "914.5878",
            "5. volume": "5669049"
        },
        "2025-12-31": {
            "1. open": "914.5878",
            "2. high": "919.8564",
            "3. low": "910.5364",
            "4. close": "912.7535",
            "5. volume": "4107995"
        },
        "2025-12-30": {
            "1. open": "912.7535",
            "2. high": "917.0687",
            "3. low": "906.3386",
            "4. close": "914.5058",
            "5. volume": "3995132"
        },
        "2025-12-29": {
            "1. open": "914.5058",
            "2. high": "940.0295",
            "3. low": "906.3991",
            "4. close": "934.2702",
            "5. volume": "5817116"
        },
        "2025-12-26": {
            "1. open": "934.2702",
            "2. high": "963.5492",
            "3. low": "930.0291",
            "4. close": "957.6389",
            "5. volume": "7801304"
        },
        "2025-12-25": {
            "1. open": "957.6389",
            "2. high": "981.6008",
            "3. low": "953.3580",
            "4. close": "974.6118",
            "5. volume": "7112816"
        },
        "2025-12-24": {
            "1. open": "974.6118",
            "2. high": "995.5820",
            "3. low": "974.5658",
            "4. close": "990.5174",
            "5. volume": "4998928"
        },
        "2025-12-23": {
            "1. open": "990.5174",
            "2. high": "996.6156",
            "3. low": "972.6996",
            "4. close": "973.2674",
            "5. volume": "6673399"
        },
        "2025-12-22": {
            "1. open": "973.2674",
            "2. high": "991.4078",
            "3. low": "968.3610",
            "4. close": "987.6071",
            "5. volume": "4075417"
        },
        "2025-12-19": {
            "1. open": "987.6071",
            "2. high": "997.7251",
            "3. low": "977.2054",
            "4. close": "996.3514",
            "5. volume": "7339849"
        },
        "2025-12-18": {
            "1. open": "996.3514",
            "2. high": "996.7609",
            "3. low": "977.4542",
            "4. close": "983.1629",
            "5. volume": "4001739"
        },
        "2025-12-17": {
            "1. open": "983.1629",
            "2. high": "986.3103",
            "3. low": "961.4877",
            "4. close": "962.1469",
            "5. volume": "6854702"
        },
        "2025-12-16": {
            "1. open": "962.1469",
            "2. high": "965.9785",
            "3. low": "956.8727",
            "4. close": "964.5017",
            "5. volume": "5249562"
        },
        "2025-12-15": {
            "1. open": "964.5017",
            "2. high": "971.5245",
            "3. low": "957.9749",
            "4. close": "969.4463",
            "5. volume": "5209093"
        },
        "2025-12-12": {
            "1. open": "969.4463",
            "2. high": "979.4745",
            "3. low": "967.6366",
            "4. close": "970.1873",
            "5. volume": "5496361"
        },
        "2025-12-11": {
            "1. open": "970.1873",
            "2. high": "989.8476",
            "3. low": "970.1672",
            "4. close": "983.1927",
            "5. volume": "3384676"
        },
        "2025-12-10": {
            "1. open": "983.1927",
            "2. high": "989.4704",
            "3. low": "967.7528",
            "4. close": "968.3231",
            "5. volume": "4623648"
        },
        "2025-12-09": {
            "1. open": "968.3231",
            "2. high": "981.3482",
            "3. low": "965.5122",
            "4. close": "976.7479",
            "5. volume": "4957796"
        },
        "2025-12-08": {
            "1. open": "976.7479",
            "2. high": "979.9966",
            "3. low": "955.8438",
            "4. close": "956.6967",
            "5. volume": "5169496"
        },
        "2025-12-05": {
            "1. open": "956.6967",
            "2. high": "958.7300",
            "3. low": "952.5045",
            "4. close": "953.2399",
            "5. volume": "4989962"
        },
        "2025-12-04": {
            "1. open": "953.2399",
            "2. high": "958.2572",
            "3. low": "949.8525",
            "4. close": "956.8166",
            "5. volume": "5402891"
        },
        "2025-12-03": {
            "1. open": "956.8166",
            "2. high": "983.3423",
            "3. low": "948.0615",
            "4. close": "976.4786",
            "5. volume": "5055057"
        },
        "2025-12-02": {
            "1. open": "976.4786",
            "2. high": "977.4062",
            "3. low": "967.6809",
            "4. close": "974.7390",
            "5. volume": "7585917"
        },
        "2025-12-01": {
            "1. open": "974.7390",
            "2. high": "989.8322",
            "3. low": "965.3063",
            "4. close": "988.2188",
            "5. volume": "6121438"
        },
        "2025-11-28": {
            "1. open": "988.2188",
            "2. high": "998.0574",
            "3. low": "986.8928",
            "4. close": "987.7467",
            "5. volume": "6324735"
        },
        "2025-11-27": {
            "1. open": "987.7467",
            "2. high": "987.8437",
            "3. low": "978.9873",
            "4. close": "980.9700",
            "5. volume": "6600953"
        },
        "2025-11-26": {
            "1. open": "980.9700",
            "2. high": "1002.8929",
            "3. low": "977.7749",
            "4. close": "995.2553",
            "5. volume": "6989542"
        },
        "2025-11-25": {
            "1. open": "995.2553",
            "2. high": "1008.5181",
            "3. low": "990.7821",
            "4. close": "1004.3458",
            "5. volume": "7652923"
        },
        "2025-11-24": {
            "1. open": "1004.3458",
            "2. high": "1005.1584",
            "3. low": "992.3823",
            "4. close": "996.2778",
            "5. volume": "6599192"
        },
        "2025-11-21": {
            "1. open": "996.2778",
            "2. high": "1000.5824",
            "3. low": "985.4335",
            "4. close": "988.4310",
            "5. volume": "7116545"
        },
        "2025-11-20": {
            "1. open": "988.4310",
            "2. high": "990.6740",
            "3. low": "984.3913",
            "4. close": "988.2551",
            "5. volume": "5474270"
        },
        "2025-11-19": {
            "1. open": "988.2551",
            "2. high": "991.4960",
            "3. low": "979.2598",
            "4. close": "990.3764",
            "5. volume": "3676154"
        },
        "2025-11-18": {
            "1. open": "990.3764",
            "2. high": "1002.5422",
            "3. low": "984.3333",
            "4. close": "987.8045",
            "5. volume": "3943807"
        },
        "2025-11-17": {
            "1. open": "987.8045",
            "2. high": "1002.6992",
            "3. low": "978.2115",
            "4. close": "1000.6632",
            "5. volume": "4439522"
        },
        "2025-11-14": {
            "1. open": "1000.6632",
            "2. high": "1002.3685",
            "3. low": "984.0117",
            "4. close": "989.7955",
            "5. volume": "5607447"
        },
        "2025-11-13": {
            "1. open": "989.7955",
            "2. high": "990.3083",
            "3. low": "963.3549",
            "4. close": "971.6992",
            "5. volume": "5357888"
        },
        "2025-11-12": {
            "1. open": "971.6992",
            "2. high": "972.3784",
            "3. low": "945.2404",
            "4. close": "947.7022",
            "5. volume": "6194331"
        },
        "2025-11-11": {
            "1. open": "947.7022",
            "2. high": "950.3722",
            "3. low": "923.6118",
            "4. close": "923.6741",
            "5. volume": "5809469"
        },
        "2025-11-10": {
            "1. open": "923.6741",
            "2. high": "930.1324",
            "3. low": "890.0327",
            "4. close": "892.6427",
            "5. volume": "5973517"
        },
        "2025-11-07": {
            "1. open": "892.6427",
            "2. high": "893.8804",
            "3. low": "880.4086",
            "4. close": "883.2048",
            "5. volume": "8035218"
        },
        "2025-11-06": {
            "1. open": "883.2048",
            "2. high": "887.5011",
            "3. low": "862.2613",
            "4. close": "866.0454",
            "5. volume": "6689493"
        },
        "2025-11-05": {
            "1. open": "866.0454",
            "2. high": "867.2862",
            "3. low": "848.9896",
            "4. close": "850.4144",
            "5. volume": "3339549"
        },
        "2025-11-04": {
            "1. open": "850.4144",
            "2. high": "851.6329",
            "3. low": "820.3538",
            "4. close": "822.7606",
            "5. volume": "3988384"
        },
        "2025-11-03": {
            "1. open": "822.7606",
            "2. high": "853.7382",
            "3. low": "822.3634",
            "4. close": "851.8008",
            "5. volume": "6583349"
        },
        "2025-10-31": {
            "1. open": "851.8008",
            "2. high": "875.4820",
            "3. low": "851.5749",
            "4. close": "864.9749",
            "5. volume": "7915822"
        },
        "2025-10-30": {
            "1. open": "864.9749",
            "2. high": "874.5305",
            "3. low": "853.0701",
            "4. close": "856.1321",
            "5. volume": "6279863"
        },
        "2025-10-29": {
            "1. open": "856.1321",
            "2. high": "866.3443",
            "3. low": "852.2892",
            "4. close": "862.4758",
            "5. volume": "6849429"
        },
        "2025-10-28": {
            "1. open": "862.4758",
            "2. high": "877.9732",
            "3. low": "860.7473",
            "4. close": "873.8219",
            "5. volume": "5004162"
        },
        "2025-10-27": {
            "1. open": "873.8219",
            "2. high": "876.1035",
            "3. low": "853.5405",
            "4. close": "858.6993",
            "5. volume": "5214452"
        },
        "2025-10-24": {
            "1. open": "858.6993",
            "2. high": "866.6601",
            "3. low": "852.6849",
            "4. close": "852.7632",
            "5. volume": "6608326"
        }
    }
}
